ai_develop_assistant/AIDevlopStudy.py
ai_develop_assistant/__init__.py
ai_develop_assistant/__main__.py
ai_develop_assistant/mcp_adapter.py
ai_develop_assistant-1.5.0.dist-info/METADATA
ai_develop_assistant-1.5.0.dist-info/WHEEL
ai_develop_assistant-1.5.0.dist-info/entry_points.txt
ai_develop_assistant-1.5.0.dist-info/licenses/LICENSE
ai_develop_assistant-1.5.0.dist-info/RECORD
