Metadata-Version: 2.4
Name: ai-develop-assistant
Version: 1.5.0
Summary: 协助AI开发者进行智能化需求完善、模块设计、技术架构设计的MCP工具
Project-URL: Homepage, https://github.com/jiemobasixiangcai/ai-develop-assistant
Project-URL: Repository, https://github.com/jiemobasixiangcai/ai-develop-assistant
Author-email: jiemobasixiangcai <39970068+jiemobasixiangcai@users.noreply.github.com>
License: MIT License
License-File: LICENSE
Requires-Python: >=3.8
Requires-Dist: mcp>=1.9.0
Requires-Dist: pydantic>=2.7.0
Requires-Dist: typing-extensions>=4.12.0
